Metadata-Version: 2.1
Name: odoo10-addon-shopinvader-cart-expiry
Version: 10.0.1.1.0
Summary: Shopinvader module to manage an expiry delay on cart
Home-page: http://www.shopinvader.com
Author: ACSONE SA/NV
License: AGPL-3
Platform: UNKNOWN
Classifier: Programming Language :: Python
Classifier: Framework :: Odoo
Classifier: License :: OSI Approved :: GNU Affero General Public License v3
Requires-Python: ~=2.7
Requires-Dist: odoo10-addon-queue-job
Requires-Dist: odoo10-addon-shopinvader
Requires-Dist: odoo (<10.1dev,>=10.0)
